hc_mcp_confluence/__init__.py
hc_mcp_confluence/server.py
hc_mcp_confluence-2025.4.1.dist-info/METADATA
hc_mcp_confluence-2025.4.1.dist-info/WHEEL
hc_mcp_confluence-2025.4.1.dist-info/entry_points.txt
hc_mcp_confluence-2025.4.1.dist-info/RECORD
