Metadata-Version: 2.4
Name: hc-mcp-confluence
Version: 2025.4.1
Summary: HC MCP server for Confluence integration
Author-email: Erik Meinders <erik@easytocloud.com>
Requires-Python: >=3.10
Requires-Dist: atlassian-python-api>=3.41.6
Requires-Dist: mcp-config-manager>=0.1.0
Requires-Dist: mcp>=1.2.0
